piqture/__init__.py
piqture/version.txt
piqture/data_loader/__init__.py
piqture/data_loader/mnist_data_loader.py
piqture/embeddings/__init__.py
piqture/embeddings/amplitude_encoder.py
piqture/embeddings/angle_encoding.py
piqture/embeddings/image_embedding.py
piqture/embeddings/image_embeddings/__init__.py
piqture/embeddings/image_embeddings/brqi.py
piqture/embeddings/image_embeddings/frqi.py
piqture/embeddings/image_embeddings/ineqr.py
piqture/embeddings/image_embeddings/mcrqi.py
piqture/embeddings/image_embeddings/neqr.py
piqture/gates/__init__.py
piqture/gates/two_qubit_unitary.py
piqture/gates/unitary_block.py
piqture/mixin/__init__.py
piqture/mixin/image_embedding_mixin.py
piqture/neural_networks/__init__.py
piqture/neural_networks/qcnn.py
piqture/neural_networks/quantum_autoencoder.py
piqture/neural_networks/quantum_neural_network.py
piqture/neural_networks/layers/__init__.py
piqture/neural_networks/layers/base_layer.py
piqture/neural_networks/layers/convolutional_layer.py
piqture/neural_networks/layers/fully_connected_layer.py
piqture/neural_networks/layers/pooling_layer.py
piqture/tensor_networks/__init__.py
piqture/tensor_networks/base_tensor_network.py
piqture/tensor_networks/mera.py
piqture/tensor_networks/mps.py
piqture/tensor_networks/peps.py
piqture/tensor_networks/ttn.py
piqture/transforms/__init__.py
piqture/transforms/transforms.py
piqture/variational_classifiers/__init__.py
piqture/variational_classifiers/data_reuploading.py
piqture/variational_classifiers/kernel_estimator.py
piqture/variational_classifiers/variational_classifier.py
piqture-0.2.0.dist-info/licenses/LICENSE
tests/__init__.py
tests/conftest.py
tests/embeddings/__init__.py
tests/embeddings/test_angle_encoding.py
tests/embeddings/image_embeddings/__init__.py
tests/embeddings/image_embeddings/test_brqi.py
tests/embeddings/image_embeddings/test_frqi.py
tests/embeddings/image_embeddings/test_ineqr.py
tests/embeddings/image_embeddings/test_neqr.py
tests/gates/__init__.py
tests/gates/test_two_qubit_unitary.py
piqture-0.2.0.dist-info/METADATA
piqture-0.2.0.dist-info/WHEEL
piqture-0.2.0.dist-info/top_level.txt
piqture-0.2.0.dist-info/RECORD
