Metadata-Version: 2.4
Name: piQture
Version: 0.2.0
Summary: piQture: A QML library for Image Processing
Author-email: Saasha Joshi <saashajoshi08@gmail.com>
License: Apache-2.0
Project-URL: Homepage, https://github.com/SaashaJoshi/piQture
Requires-Python: >=3.10
License-File: LICENSE
Requires-Dist: matplotlib==3.7.5
Requires-Dist: qiskit>=2.0.0
Requires-Dist: setuptools>=80.1.0
Requires-Dist: torchvision==0.22.1
Dynamic: license-file
